actions/__init__.py
actions/context.py
actions/core.py
actions/py.typed
actions_tools-0.2.2.dist-info/licenses/LICENSE
actions_tools-0.2.2.dist-info/METADATA
actions_tools-0.2.2.dist-info/WHEEL
actions_tools-0.2.2.dist-info/top_level.txt
actions_tools-0.2.2.dist-info/RECORD
