Metadata-Version: 2.4
Name: actions-tools
Version: 0.2.2
Summary: A Typed Python GitHub Actions Tookit similar to actions/toolkit.
Author: Shane
License: GPL-3.0
Project-URL: Homepage, https://cssnr.com/
Project-URL: Documentation, https://actions-tools.cssnr.com/
Project-URL: Source, https://github.com/cssnr/actions-tools
Project-URL: Issues, https://github.com/cssnr/actions-tools/issues
Project-URL: Funding, https://ko-fi.com/cssnr
Classifier: Programming Language :: Python
Classifier: Programming Language :: Python :: 3
Classifier: Programming Language :: Python :: 3 :: Only
Classifier: Programming Language :: Python :: 3.10
Classifier: Programming Language :: Python :: 3.11
Classifier: Programming Language :: Python :: 3.12
Classifier: Programming Language :: Python :: 3.13
Classifier: Programming Language :: Python :: 3.14
Classifier: Operating System :: OS Independent
Classifier: License :: OSI Approved :: GNU Lesser General Public License v3 (LGPLv3)
Classifier: Natural Language :: English
Requires-Python: >=3.10
License-File: LICENSE
Requires-Dist: PyYAML
Provides-Extra: github
Requires-Dist: PyGithub<3,>=2; extra == "github"
Dynamic: license-file
